{
  "schemaVersion": 1,
  "id": "keeptrident",
  "version": "${version}",
  "name": "Keep Trident",
  "description": "${description}",
  "authors": [
    "Deadly Artist"
  ],
  "contact": {
    "homepage": "https://deadlyartist.com/",
    "sources": "https://github.com/DeadlyArtist/KeepTrident"
  },
  "license": "MIT",
  "icon": "icon.png",
  "environment": "*",
  "entrypoints": {
    "main": [
      "keeptrident.fabric.KPTridentFabric"
    ],
    "client": [
      "keeptrident.fabric.client.ExampleModFabricClient"
    ]
  },
  "mixins": [
    "keeptrident.mixins.json"
  ],
  "depends": {
    "fabricloader": ">=0.17.3",
    "minecraft": "~1.19.2",
    "java": ">=17",
    "fabric-api": "*"
  },
  "suggests": {
    "another-mod": "*"
  }
}
